LICENSE
MANIFEST.in
README.md
setup.cfg
setup.py
images/logo.png
talos/__init__.py
talos/talos.py
talos/talos_run.py
talos/algorithm/__init__.py
talos/algorithm/hill_climbing.py
talos/algorithm/mapper.py
talos/algorithm/parameters.py
talos/algorithm/search_loop.py
talos/algorithm/step.py
talos/algorithm/distributed_algorithm/__init__.py
talos/algorithm/distributed_algorithm/search_loop.py
talos/algorithm/distributed_algorithm/step.py
talos/fitness/__init__.py
talos/fitness/bic.py
talos/fitness/evaluation.py
talos/fitness/minimise_nodes.py
talos/fitness/num_params.py
talos/fitness/predict_time.py
talos/fitness/progsys.py
talos/fitness/pymax.py
talos/fitness/sequence_match.py
talos/fitness/string_match.py
talos/fitness/training_time.py
talos/fitness/base_ff_classes/__init__.py
talos/fitness/base_ff_classes/base_ff.py
talos/fitness/base_ff_classes/ff_template.py
talos/fitness/base_ff_classes/moo_ff.py
talos/fitness/multi_objective/__init__.py
talos/fitness/multi_objective/binary_phenotype_to_float.py
talos/fitness/multi_objective/singlefit_autoencoders.py
talos/fitness/multi_objective/singlefit_multiobj.py
talos/fitness/multi_objective/zdt1.py
talos/fitness/regex/RegexEval.py
talos/fitness/regex/__init__.py
talos/fitness/regex/testing/RegexTest.py
talos/fitness/regex/testing/RegexTestGenerator.py
talos/fitness/regex/testing/RegexTimer.py
talos/fitness/regex/testing/__init__.py
talos/fitness/supervised_learning/__init__.py
talos/fitness/supervised_learning/boolean_problem.py
talos/fitness/supervised_learning/classification.py
talos/fitness/supervised_learning/if_else_classifier.py
talos/fitness/supervised_learning/regression.py
talos/fitness/supervised_learning/regression_random_polynomial.py
talos/fitness/supervised_learning/supervised_learning.py
talos/fitness/supervised_learning/supervised_learning_backup.py
talos/grammars/autoencoders.bnf
talos/grammars/autoencoders.pybnf
talos/grammars/autoencoders_v2.pybnf
talos/grammars/autoencoders_v3.pybnf
talos_automl.egg-info/PKG-INFO
talos_automl.egg-info/SOURCES.txt
talos_automl.egg-info/dependency_links.txt
talos_automl.egg-info/requires.txt
talos_automl.egg-info/top_level.txt