Metadata-Version: 2.1
Name: talos-automl
Version: 0.0.4
Summary: Talos: Automated Machine Learning (AutoML) library for One-Class Learning
Home-page: https://github.com/luisferreira97/talos
Author: Luís Ferreira
Author-email: luis_ferreira223@hotmail.com
License: UNKNOWN
Keywords: automl,machine learning,one-class learning,one-class classification,autoencoder,isolation forest,one-class svm
Platform: UNKNOWN
Classifier: Programming Language :: Python :: 3
Classifier: License :: OSI Approved :: MIT License
Classifier: Operating System :: OS Independent
Requires-Python: >=3.6
License-File: LICENSE
